[{"id":11000100,"map_id":"","name":1,"desc":113,"category":0,"level":1,"term_id":"","sort_id":14},{"id":11000200,"map_id":"","name":2,"desc":114,"category":0,"level":1,"term_id":"","sort_id":15},{"id":11000300,"map_id":"","name":3,"desc":115,"category":0,"level":1,"term_id":"","sort_id":16},{"id":11000400,"map_id":"","name":4,"desc":116,"category":0,"level":1,"term_id":"","sort_id":17},{"id":11000500,"map_id":"","name":5,"desc":117,"category":0,"level":1,"term_id":"","sort_id":18},{"id":11000600,"map_id":"","name":6,"desc":118,"category":0,"level":1,"term_id":"","sort_id":19},{"id":11000700,"map_id":"","name":7,"desc":119,"category":0,"level":1,"term_id":"","sort_id":20},{"id":11000800,"map_id":"","name":8,"desc":120,"category":0,"level":1,"term_id":"","sort_id":21},{"id":11000900,"map_id":"","name":9,"desc":121,"category":0,"level":1,"term_id":"","sort_id":22},{"id":11001000,"map_id":"","name":10,"desc":122,"category":0,"level":1,"term_id":"","sort_id":23},{"id":11001100,"map_id":"","name":11,"desc":123,"category":0,"level":1,"term_id":"","sort_id":24},{"id":11001200,"map_id":"","name":12,"desc":124,"category":0,"level":1,"term_id":"","sort_id":25},{"id":11001300,"map_id":"","name":13,"desc":125,"category":0,"level":1,"term_id":"","sort_id":26},{"id":11001400,"map_id":"","name":14,"desc":126,"category":0,"level":1,"term_id":"","sort_id":27},{"id":11001500,"map_id":"","name":15,"desc":127,"category":0,"level":1,"term_id":"","sort_id":28},{"id":11001600,"map_id":"","name":16,"desc":128,"category":0,"level":1,"term_id":"","sort_id":29},{"id":11001700,"map_id":"","name":17,"desc":129,"category":0,"level":1,"term_id":"","sort_id":30},{"id":11001800,"map_id":"","name":18,"desc":130,"category":0,"level":1,"term_id":"","sort_id":31},{"id":11001900,"map_id":"","name":19,"desc":131,"category":0,"level":1,"term_id":"","sort_id":32},{"id":11002000,"map_id":"","name":20,"desc":132,"category":0,"level":1,"term_id":"","sort_id":33},{"id":11002100,"map_id":"","name":21,"desc":133,"category":0,"level":1,"term_id":"","sort_id":34},{"id":11002200,"map_id":"","name":22,"desc":134,"category":0,"level":1,"term_id":"","sort_id":35},{"id":11002300,"map_id":"","name":23,"desc":135,"category":0,"level":1,"term_id":"","sort_id":36},{"id":11002400,"map_id":"","name":24,"desc":136,"category":0,"level":1,"term_id":"","sort_id":37},{"id":11002500,"map_id":"","name":25,"desc":137,"category":0,"level":1,"term_id":"","sort_id":38},{"id":11002600,"map_id":"","name":26,"desc":138,"category":0,"level":1,"term_id":"","sort_id":39},{"id":11002700,"map_id":"","name":27,"desc":139,"category":0,"level":1,"term_id":"","sort_id":40},{"id":11002800,"map_id":"","name":28,"desc":140,"category":0,"level":1,"term_id":"","sort_id":41},{"id":11002900,"map_id":"","name":29,"desc":141,"category":0,"level":1,"term_id":"","sort_id":42},{"id":11003000,"map_id":"","name":30,"desc":142,"category":0,"level":1,"term_id":"","sort_id":43},{"id":11003100,"map_id":"","name":31,"desc":143,"category":0,"level":1,"term_id":"","sort_id":44},{"id":11003200,"map_id":"","name":32,"desc":144,"category":0,"level":1,"term_id":"","sort_id":45},{"id":11003300,"map_id":"","name":33,"desc":145,"category":0,"level":1,"term_id":"","sort_id":46},{"id":11003400,"map_id":"","name":34,"desc":146,"category":0,"level":1,"term_id":"","sort_id":47},{"id":11003500,"map_id":"","name":35,"desc":147,"category":0,"level":1,"term_id":"","sort_id":48},{"id":11003600,"map_id":"","name":36,"desc":148,"category":0,"level":1,"term_id":"","sort_id":49},{"id":11003700,"map_id":"","name":37,"desc":149,"category":0,"level":1,"term_id":"","sort_id":50},{"id":11003800,"map_id":"","name":38,"desc":150,"category":0,"level":1,"term_id":"","sort_id":51},{"id":11003900,"map_id":"","name":39,"desc":151,"category":0,"level":1,"term_id":"","sort_id":52},{"id":11004000,"map_id":"","name":40,"desc":152,"category":0,"level":1,"term_id":"","sort_id":53},{"id":11004100,"map_id":"","name":41,"desc":153,"category":0,"level":1,"term_id":"","sort_id":54},{"id":11004200,"map_id":"","name":42,"desc":154,"category":0,"level":1,"term_id":"","sort_id":55},{"id":11004300,"map_id":"","name":43,"desc":155,"category":0,"level":1,"term_id":"","sort_id":56},{"id":11004400,"map_id":"","name":44,"desc":156,"category":0,"level":1,"term_id":"","sort_id":57},{"id":11004500,"map_id":"","name":45,"desc":157,"category":0,"level":1,"term_id":"","sort_id":58},{"id":11004600,"map_id":"","name":46,"desc":158,"category":0,"level":1,"term_id":"","sort_id":59},{"id":11004700,"map_id":"","name":47,"desc":159,"category":0,"level":1,"term_id":"","sort_id":60},{"id":11004800,"map_id":"","name":48,"desc":160,"category":0,"level":1,"term_id":"","sort_id":61},{"id":11004900,"map_id":"","name":49,"desc":161,"category":0,"level":1,"term_id":"","sort_id":62},{"id":11005000,"map_id":"","name":50,"desc":162,"category":0,"level":1,"term_id":"","sort_id":63},{"id":11005100,"map_id":"","name":51,"desc":163,"category":0,"level":1,"term_id":"","sort_id":64},{"id":11005200,"map_id":"","name":52,"desc":164,"category":0,"level":1,"term_id":"","sort_id":65},{"id":11005300,"map_id":"","name":53,"desc":165,"category":0,"level":1,"term_id":"","sort_id":66},{"id":11005400,"map_id":"","name":54,"desc":166,"category":0,"level":1,"term_id":"","sort_id":67},{"id":11005500,"map_id":"","name":55,"desc":167,"category":0,"level":1,"term_id":"","sort_id":68},{"id":11005600,"map_id":"","name":56,"desc":168,"category":0,"level":1,"term_id":"","sort_id":69},{"id":11005700,"map_id":"","name":57,"desc":169,"category":0,"level":1,"term_id":"","sort_id":70},{"id":11005800,"map_id":"","name":58,"desc":170,"category":0,"level":1,"term_id":"","sort_id":71},{"id":11005900,"map_id":"","name":59,"desc":171,"category":0,"level":1,"term_id":"","sort_id":72},{"id":11006000,"map_id":"","name":60,"desc":172,"category":0,"level":1,"term_id":"","sort_id":73},{"id":11006100,"map_id":"","name":61,"desc":173,"category":0,"level":1,"term_id":"","sort_id":74},{"id":11006200,"map_id":"","name":62,"desc":174,"category":0,"level":1,"term_id":"","sort_id":75},{"id":11006300,"map_id":"","name":63,"desc":175,"category":0,"level":1,"term_id":"","sort_id":76},{"id":11006400,"map_id":"","name":64,"desc":176,"category":0,"level":1,"term_id":"","sort_id":77},{"id":11006500,"map_id":"","name":65,"desc":177,"category":0,"level":1,"term_id":"","sort_id":78},{"id":11006600,"map_id":"","name":66,"desc":178,"category":0,"level":1,"term_id":"","sort_id":79},{"id":11006700,"map_id":"","name":67,"desc":179,"category":0,"level":1,"term_id":"","sort_id":80},{"id":11006800,"map_id":"","name":68,"desc":180,"category":0,"level":1,"term_id":"","sort_id":81},{"id":11006900,"map_id":"","name":69,"desc":181,"category":0,"level":1,"term_id":"","sort_id":82},{"id":11007000,"map_id":"","name":70,"desc":182,"category":0,"level":1,"term_id":"","sort_id":83},{"id":11007100,"map_id":"","name":71,"desc":183,"category":0,"level":1,"term_id":"","sort_id":84},{"id":11007200,"map_id":"","name":72,"desc":184,"category":0,"level":1,"term_id":"","sort_id":85},{"id":11007300,"map_id":"","name":73,"desc":185,"category":0,"level":1,"term_id":"","sort_id":86},{"id":11007400,"map_id":"","name":74,"desc":186,"category":0,"level":1,"term_id":"","sort_id":87},{"id":11007500,"map_id":"","name":75,"desc":187,"category":0,"level":1,"term_id":"","sort_id":88},{"id":11007600,"map_id":"","name":76,"desc":188,"category":0,"level":1,"term_id":"","sort_id":89},{"id":11007700,"map_id":"","name":77,"desc":189,"category":0,"level":1,"term_id":"","sort_id":90},{"id":11007800,"map_id":"","name":78,"desc":190,"category":0,"level":1,"term_id":"","sort_id":91},{"id":11007900,"map_id":"","name":79,"desc":191,"category":0,"level":1,"term_id":"","sort_id":92},{"id":11008000,"map_id":"","name":80,"desc":192,"category":0,"level":1,"term_id":"","sort_id":93},{"id":11008100,"map_id":"","name":81,"desc":193,"category":0,"level":1,"term_id":"","sort_id":94},{"id":11008200,"map_id":"","name":82,"desc":194,"category":2,"level":1,"term_id":"","sort_id":86},{"id":11008300,"map_id":"","name":83,"desc":195,"category":2,"level":1,"term_id":"","sort_id":87},{"id":11008400,"map_id":"","name":84,"desc":196,"category":2,"level":1,"term_id":"","sort_id":88},{"id":11008500,"map_id":"","name":85,"desc":197,"category":2,"level":1,"term_id":"","sort_id":89},{"id":11008600,"map_id":"","name":225,"desc":269,"category":0,"level":1,"term_id":"","sort_id":90},{"id":11008700,"map_id":"","name":226,"desc":270,"category":0,"level":1,"term_id":"","sort_id":91},{"id":11008800,"map_id":"","name":227,"desc":271,"category":0,"level":1,"term_id":"","sort_id":92},{"id":11008900,"map_id":"","name":228,"desc":272,"category":0,"level":1,"term_id":"","sort_id":93},{"id":11009000,"map_id":"","name":229,"desc":273,"category":0,"level":1,"term_id":"","sort_id":94},{"id":11009100,"map_id":"","name":230,"desc":274,"category":0,"level":1,"term_id":"","sort_id":95},{"id":11009200,"map_id":"","name":231,"desc":275,"category":0,"level":1,"term_id":"","sort_id":96},{"id":11009300,"map_id":"","name":232,"desc":276,"category":0,"level":1,"term_id":"","sort_id":97},{"id":11009400,"map_id":"","name":233,"desc":277,"category":0,"level":1,"term_id":"","sort_id":98},{"id":11009500,"map_id":"","name":234,"desc":278,"category":0,"level":1,"term_id":"","sort_id":99},{"id":11009600,"map_id":"","name":235,"desc":279,"category":0,"level":1,"term_id":"","sort_id":100},{"id":11009700,"map_id":"","name":236,"desc":280,"category":0,"level":1,"term_id":"","sort_id":101},{"id":11009800,"map_id":"","name":237,"desc":281,"category":0,"level":1,"term_id":"","sort_id":102},{"id":11009900,"map_id":"","name":238,"desc":282,"category":0,"level":1,"term_id":"","sort_id":103},{"id":11010000,"map_id":"","name":239,"desc":283,"category":0,"level":1,"term_id":"","sort_id":104},{"id":11010100,"map_id":"","name":240,"desc":284,"category":0,"level":1,"term_id":"","sort_id":105},{"id":11010200,"map_id":"","name":241,"desc":285,"category":0,"level":1,"term_id":"","sort_id":106},{"id":11010300,"map_id":"","name":242,"desc":286,"category":0,"level":1,"term_id":"","sort_id":107},{"id":11010400,"map_id":"","name":243,"desc":287,"category":0,"level":1,"term_id":"","sort_id":108},{"id":11010500,"map_id":"","name":244,"desc":288,"category":0,"level":1,"term_id":"","sort_id":109},{"id":11010600,"map_id":"","name":245,"desc":289,"category":0,"level":1,"term_id":"","sort_id":110},{"id":11010700,"map_id":"","name":246,"desc":290,"category":0,"level":1,"term_id":"","sort_id":111},{"id":11010800,"map_id":"","name":247,"desc":291,"category":0,"level":1,"term_id":"","sort_id":112},{"id":11010900,"map_id":"","name":248,"desc":292,"category":0,"level":1,"term_id":"","sort_id":113}]