[
  {
    "Type": "SBCharacterAnimationSamplingAsset",
    "Name": "ASA_HealerPod",
    "Class": "UScriptClass'SBCharacterAnimationSamplingAsset'",
    "Properties": {
      "OwnerCharacter": {
        "AssetPathName": "/Game/Blueprints/Enemy/E024_02_HealerPod/BP_HealerPod.BP_HealerPod_C",
        "SubPathString": ""
      },
      "SampleData": {
        "OverrideActionDataMap": [
          {
            "BlowDw": {
              "OverrideAttackableArea": {
                "Offset": {
                  "X": -70.0,
                  "Y": 0.0,
                  "Z": 0.0
                },
                "MinRange": 70.0,
                "MaxRange": 270.0,
                "LeftAngle": -23.0,
                "RightAngle": 23.0,
                "UpperAngle": 180.0,
                "LowerAngle": -180.0
              }
            }
          },
          {
            "CastRecoveryAround": {
              "OverrideAttackableArea": {
                "Offset": {
                  "X": 0.0,
                  "Y": 0.0,
                  "Z": 0.0
                },
                "MinRange": 35.35534,
                "MaxRange": 1035.0121,
                "LeftAngle": -0.1,
                "RightAngle": 0.1,
                "UpperAngle": 180.0,
                "LowerAngle": -180.0
              }
            }
          }
        ],
        "ActionDataGroupMap": [
          {
            "BlowDw": {
              "ActionDerivationArray": [
                {
                  "Key": {
                    "Type": "ESBCharacterAnimationSamplingResultActionDerivedType::Default",
                    "ThresholdVelocity": 0.0,
                    "CommandArray": []
                  },
                  "ActionData": {
                    "AttackInfos": [
                      {
                        "AnimSequenceName": "All",
                        "NotifyName": "All",
                        "AttackRange": {
                          "LeftAngle": -32.34746,
                          "RightAngle": 17.241472,
                          "MinRange": 79.05694,
                          "MaxRange": 237.17082,
                          "Offset": {
                            "X": 0.0,
                            "Y": 0.0,
                            "Z": 0.0
                          }
                        },
                        "HomingRange": 0.0,
                        "AttackRangePitchAngle": {
                          "UpperAngle": 180.0,
                          "LowerAngle": -180.0
                        },
                        "BeginAttackTime": 1.0499579,
                        "BeginAttackLocation": {
                          "X": 79.94675,
                          "Y": 3.8146973E-06,
                          "Z": 0.0
                        },
                        "EndAttackTime": 1.1666203,
                        "EndAttackLocation": {
                          "X": 79.99999,
                          "Y": 3.8184226E-06,
                          "Z": 0.0
                        }
                      }
                    ],
                    "UseAnimationAssetPath": [],
                    "AnimTime": 1.9832569,
                    "LocationAndRotation": {
                      "Location": {
                        "X": 79.99999,
                        "Y": 3.8184226E-06,
                        "Z": 0.0
                      },
                      "Rotation": {
                        "Pitch": 0.0,
                        "Yaw": 0.0,
                        "Roll": 0.0
                      }
                    },
                    "AdjustRootMotionInfoArray": [
                      {
                        "AnimSequenceName": "AS_E024_FFF_ACT_BlowDw",
                        "NotifyName": "SBAnimNotifyState_AdjustEnemyRootMotion_0",
                        "BeginNotifyTime": 0.99995977,
                        "BeginNotifyTransform": {
                          "Rotation": {
                            "X": 0.0,
                            "Y": 0.0,
                            "Z": 0.0,
                            "W": 1.0,
                            "IsNormalized": true,
                            "Size": 1.0,
                            "SizeSquared": 1.0
                          },
                          "Translation": {
                            "X": 0.0,
                            "Y": 0.0,
                            "Z": 0.0
                          },
                          "Scale3D": {
                            "X": 1.0,
                            "Y": 1.0,
                            "Z": 1.0
                          }
                        },
                        "EndNotifyTime": 1.1666203,
                        "EndNotifyTransform": {
                          "Rotation": {
                            "X": 0.0,
                            "Y": 0.0,
                            "Z": 0.0,
                            "W": 1.0,
                            "IsNormalized": true,
                            "Size": 1.0,
                            "SizeSquared": 1.0
                          },
                          "Translation": {
                            "X": 79.99999,
                            "Y": 3.8184226E-06,
                            "Z": 0.0
                          },
                          "Scale3D": {
                            "X": 1.0,
                            "Y": 1.0,
                            "Z": 1.0
                          }
                        },
                        "Settings": {
                          "AdjustVelocitySettings": {
                            "AdjustType": "ESBAdjustRootMotionAdjustType::Linear"
                          },
                          "TargetLocationSettings": {
                            "TargetType": "ESBAdjustRootMotionTargetType::Default",
                            "TargetDistanceRatio": 0.0,
                            "TargetLocationOffsetZ": 0.0,
                            "RequiredStartLocationOffsetZ": 0.0,
                            "TraceTargetBelowHeight": 1000.0,
                            "AdjustRangeMin": 70.0,
                            "AdjustRangeMax": 270.0,
                            "YawAngleMax": 45.0,
                            "PitchAngleMax": 90.0,
                            "ZAxisMode": "ESBAdjustRootMotionZAxisMode::NoAdjustZAxis"
                          },
                          "FacingSettings": {
                            "FacingRotationRate": 180.0,
                            "RotationType": "ESBCharacterAdjustRootMotion_Facing_RotationType::MoveDirection"
                          },
                          "FollowingSettings": {
                            "FollowTime": 0.0,
                            "FollowVelocity": 0.0
                          },
                          "ScaleRatio": {
                            "X": 1.0,
                            "Y": 1.0,
                            "Z": 1.0
                          },
                          "TargetLocationOffsetSocketName": "None",
                          "TargetLocationOffset": {
                            "X": -80.0,
                            "Y": 0.0,
                            "Z": 60.0
                          },
                          "bEnablePredictTarget": true,
                          "TargetIndex": 0
                        }
                      }
                    ],
                    "FaceTargetInfoArray": [
                      {
                        "AnimSequenceName": "AS_E024_FFF_ACT_BlowDw",
                        "NotifyName": "NST_FaceTarget_C_0",
                        "BeginNotifyTime": 0.016666,
                        "EndNotifyTime": 0.0,
                        "YawOffset": 0.0
                      }
                    ],
                    "ProjectileRange": 3000.0
                  }
                }
              ]
            }
          },
          {
            "LightStraight": {
              "ActionDerivationArray": [
                {
                  "Key": {
                    "Type": "ESBCharacterAnimationSamplingResultActionDerivedType::Default",
                    "ThresholdVelocity": 0.0,
                    "CommandArray": []
                  },
                  "ActionData": {
                    "AttackInfos": [],
                    "UseAnimationAssetPath": [],
                    "AnimTime": 3.8998396,
                    "LocationAndRotation": {
                      "Location": {
                        "X": 0.0,
                        "Y": 0.0,
                        "Z": 0.0
                      },
                      "Rotation": {
                        "Pitch": 0.0,
                        "Yaw": 0.0,
                        "Roll": 0.0
                      }
                    },
                    "AdjustRootMotionInfoArray": [],
                    "FaceTargetInfoArray": [
                      {
                        "AnimSequenceName": "AS_E024_FFF_ACT_Charge",
                        "NotifyName": "NST_FaceTarget_C_0",
                        "BeginNotifyTime": 0.6166419,
                        "EndNotifyTime": 0.0,
                        "YawOffset": 0.0
                      }
                    ],
                    "ProjectileRange": 3000.0
                  }
                }
              ]
            }
          },
          {
            "DodgeB": {
              "ActionDerivationArray": [
                {
                  "Key": {
                    "Type": "ESBCharacterAnimationSamplingResultActionDerivedType::Default",
                    "ThresholdVelocity": 0.0,
                    "CommandArray": []
                  },
                  "ActionData": {
                    "AttackInfos": [],
                    "UseAnimationAssetPath": [],
                    "AnimTime": 0.9166298,
                    "LocationAndRotation": {
                      "Location": {
                        "X": -400.00012,
                        "Y": 0.0,
                        "Z": 0.0
                      },
                      "Rotation": {
                        "Pitch": 0.0,
                        "Yaw": 0.0,
                        "Roll": 0.0
                      }
                    },
                    "AdjustRootMotionInfoArray": [],
                    "FaceTargetInfoArray": [
                      {
                        "AnimSequenceName": "AS_E024_FFF_LOC_DodgeB",
                        "NotifyName": "NST_FaceTarget_C_2",
                        "BeginNotifyTime": 0.083330005,
                        "EndNotifyTime": 0.0,
                        "YawOffset": 0.0
                      }
                    ],
                    "ProjectileRange": 3000.0
                  }
                }
              ]
            }
          },
          {
            "DodgeL": {
              "ActionDerivationArray": [
                {
                  "Key": {
                    "Type": "ESBCharacterAnimationSamplingResultActionDerivedType::Default",
                    "ThresholdVelocity": 0.0,
                    "CommandArray": []
                  },
                  "ActionData": {
                    "AttackInfos": [],
                    "UseAnimationAssetPath": [],
                    "AnimTime": 0.9166298,
                    "LocationAndRotation": {
                      "Location": {
                        "X": 0.0,
                        "Y": -399.9999,
                        "Z": 0.0
                      },
                      "Rotation": {
                        "Pitch": 0.0,
                        "Yaw": 0.0,
                        "Roll": 0.0
                      }
                    },
                    "AdjustRootMotionInfoArray": [],
                    "FaceTargetInfoArray": [
                      {
                        "AnimSequenceName": "AS_E024_FFF_LOC_DodgeL",
                        "NotifyName": "NST_FaceTarget_C_2",
                        "BeginNotifyTime": 0.09999601,
                        "EndNotifyTime": 0.0,
                        "YawOffset": 0.0
                      }
                    ],
                    "ProjectileRange": 3000.0
                  }
                }
              ]
            }
          },
          {
            "DodgeR": {
              "ActionDerivationArray": [
                {
                  "Key": {
                    "Type": "ESBCharacterAnimationSamplingResultActionDerivedType::Default",
                    "ThresholdVelocity": 0.0,
                    "CommandArray": []
                  },
                  "ActionData": {
                    "AttackInfos": [],
                    "UseAnimationAssetPath": [],
                    "AnimTime": 0.9166298,
                    "LocationAndRotation": {
                      "Location": {
                        "X": -1.0043441E-05,
                        "Y": 399.99997,
                        "Z": 0.0
                      },
                      "Rotation": {
                        "Pitch": 0.0,
                        "Yaw": 0.0,
                        "Roll": 0.0
                      }
                    },
                    "AdjustRootMotionInfoArray": [],
                    "FaceTargetInfoArray": [
                      {
                        "AnimSequenceName": "AS_E024_FFF_LOC_DodgeR",
                        "NotifyName": "NST_FaceTarget_C_2",
                        "BeginNotifyTime": 0.083330005,
                        "EndNotifyTime": 0.0,
                        "YawOffset": 0.0
                      }
                    ],
                    "ProjectileRange": 3000.0
                  }
                }
              ]
            }
          },
          {
            "ActionJumpB": {
              "ActionDerivationArray": [
                {
                  "Key": {
                    "Type": "ESBCharacterAnimationSamplingResultActionDerivedType::Default",
                    "ThresholdVelocity": 0.0,
                    "CommandArray": []
                  },
                  "ActionData": {
                    "AttackInfos": [],
                    "UseAnimationAssetPath": [],
                    "AnimTime": 0.71663785,
                    "LocationAndRotation": {
                      "Location": {
                        "X": 299.99997,
                        "Y": 1.0014512E-05,
                        "Z": 0.0
                      },
                      "Rotation": {
                        "Pitch": 0.0,
                        "Yaw": 0.0,
                        "Roll": 0.0
                      }
                    },
                    "AdjustRootMotionInfoArray": [
                      {
                        "AnimSequenceName": "AS_E024_FFF_ACT_Jump",
                        "NotifyName": "SBAnimNotifyState_AdjustEnemyRootMotion_0",
                        "BeginNotifyTime": 0.0,
                        "BeginNotifyTransform": {
                          "Rotation": {
                            "X": 0.0,
                            "Y": 0.0,
                            "Z": 0.0,
                            "W": 1.0,
                            "IsNormalized": true,
                            "Size": 1.0,
                            "SizeSquared": 1.0
                          },
                          "Translation": {
                            "X": 7.1425714,
                            "Y": 4.7683716E-07,
                            "Z": 0.0
                          },
                          "Scale3D": {
                            "X": 1.0,
                            "Y": 1.0,
                            "Z": 1.0
                          }
                        },
                        "EndNotifyTime": 0.43331593,
                        "EndNotifyTransform": {
                          "Rotation": {
                            "X": 0.0,
                            "Y": 0.0,
                            "Z": 0.0,
                            "W": 1.0,
                            "IsNormalized": true,
                            "Size": 1.0,
                            "SizeSquared": 1.0
                          },
                          "Translation": {
                            "X": 192.8494,
                            "Y": 6.67572E-06,
                            "Z": 0.0
                          },
                          "Scale3D": {
                            "X": 1.0,
                            "Y": 1.0,
                            "Z": 1.0
                          }
                        },
                        "Settings": {
                          "AdjustVelocitySettings": {
                            "AdjustType": "ESBAdjustRootMotionAdjustType::ScaleWithPlayRate"
                          },
                          "TargetLocationSettings": {
                            "TargetType": "ESBAdjustRootMotionTargetType::Default",
                            "TargetDistanceRatio": 0.0,
                            "TargetLocationOffsetZ": 0.0,
                            "RequiredStartLocationOffsetZ": 0.0,
                            "TraceTargetBelowHeight": 1000.0,
                            "AdjustRangeMin": 0.0,
                            "AdjustRangeMax": 0.0,
                            "YawAngleMax": 180.0,
                            "PitchAngleMax": 90.0,
                            "ZAxisMode": "ESBAdjustRootMotionZAxisMode::NoAdjustZAxis"
                          },
                          "FacingSettings": {
                            "FacingRotationRate": 720.0,
                            "RotationType": "ESBCharacterAdjustRootMotion_Facing_RotationType::MoveDirection"
                          },
                          "FollowingSettings": {
                            "FollowTime": 0.0,
                            "FollowVelocity": 0.0
                          },
                          "ScaleRatio": {
                            "X": 1.0,
                            "Y": 1.0,
                            "Z": 1.0
                          },
                          "TargetLocationOffsetSocketName": "None",
                          "TargetLocationOffset": {
                            "X": 0.0,
                            "Y": 0.0,
                            "Z": 0.0
                          },
                          "bEnablePredictTarget": false,
                          "TargetIndex": 0
                        }
                      },
                      {
                        "AnimSequenceName": "AS_E024_FFF_ACT_Jump",
                        "NotifyName": "SBAnimNotifyState_AdjustEnemyRootMotion_1",
                        "BeginNotifyTime": 0.39998394,
                        "BeginNotifyTransform": {
                          "Rotation": {
                            "X": 0.0,
                            "Y": 0.0,
                            "Z": 0.0,
                            "W": 1.0,
                            "IsNormalized": true,
                            "Size": 1.0,
                            "SizeSquared": 1.0
                          },
                          "Translation": {
                            "X": 178.56424,
                            "Y": 5.722046E-06,
                            "Z": 0.0
                          },
                          "Scale3D": {
                            "X": 1.0,
                            "Y": 1.0,
                            "Z": 1.0
                          }
                        },
                        "EndNotifyTime": 0.69997185,
                        "EndNotifyTransform": {
                          "Rotation": {
                            "X": 0.0,
                            "Y": 0.0,
                            "Z": 0.0,
                            "W": 1.0,
                            "IsNormalized": true,
                            "Size": 1.0,
                            "SizeSquared": 1.0
                          },
                          "Translation": {
                            "X": 299.99997,
                            "Y": 1.0014512E-05,
                            "Z": 0.0
                          },
                          "Scale3D": {
                            "X": 1.0,
                            "Y": 1.0,
                            "Z": 1.0
                          }
                        },
                        "Settings": {
                          "AdjustVelocitySettings": {
                            "AdjustType": "ESBAdjustRootMotionAdjustType::ScaleWithPlayRate"
                          },
                          "TargetLocationSettings": {
                            "TargetType": "ESBAdjustRootMotionTargetType::Default",
                            "TargetDistanceRatio": 0.0,
                            "TargetLocationOffsetZ": 0.0,
                            "RequiredStartLocationOffsetZ": 0.0,
                            "TraceTargetBelowHeight": 1000.0,
                            "AdjustRangeMin": 0.0,
                            "AdjustRangeMax": 0.0,
                            "YawAngleMax": 180.0,
                            "PitchAngleMax": 90.0,
                            "ZAxisMode": "ESBAdjustRootMotionZAxisMode::NoAdjustZAxis"
                          },
                          "FacingSettings": {
                            "FacingRotationRate": 720.0,
                            "RotationType": "ESBCharacterAdjustRootMotion_Facing_RotationType::MoveDirection"
                          },
                          "FollowingSettings": {
                            "FollowTime": 0.0,
                            "FollowVelocity": 0.0
                          },
                          "ScaleRatio": {
                            "X": 1.0,
                            "Y": 1.0,
                            "Z": 1.0
                          },
                          "TargetLocationOffsetSocketName": "None",
                          "TargetLocationOffset": {
                            "X": 0.0,
                            "Y": 0.0,
                            "Z": 0.0
                          },
                          "bEnablePredictTarget": false,
                          "TargetIndex": 0
                        }
                      }
                    ],
                    "FaceTargetInfoArray": [],
                    "ProjectileRange": 3000.0
                  }
                }
              ]
            }
          },
          {
            "CastRecoveryAround": {
              "ActionDerivationArray": [
                {
                  "Key": {
                    "Type": "ESBCharacterAnimationSamplingResultActionDerivedType::Default",
                    "ThresholdVelocity": 0.0,
                    "CommandArray": []
                  },
                  "ActionData": {
                    "AttackInfos": [
                      {
                        "AnimSequenceName": "All",
                        "NotifyName": "All",
                        "AttackRange": {
                          "LeftAngle": 180.0,
                          "RightAngle": 0.0,
                          "MinRange": 35.35534,
                          "MaxRange": 1035.0121,
                          "Offset": {
                            "X": 0.0,
                            "Y": 0.0,
                            "Z": 0.0
                          }
                        },
                        "HomingRange": 0.0,
                        "AttackRangePitchAngle": {
                          "UpperAngle": 180.0,
                          "LowerAngle": -180.0
                        },
                        "BeginAttackTime": 5.8497543,
                        "BeginAttackLocation": {
                          "X": 0.0,
                          "Y": 0.0,
                          "Z": 0.0
                        },
                        "EndAttackTime": 0.0,
                        "EndAttackLocation": {
                          "X": 0.0,
                          "Y": 0.0,
                          "Z": 0.0
                        }
                      }
                    ],
                    "UseAnimationAssetPath": [],
                    "AnimTime": 7.4163523,
                    "LocationAndRotation": {
                      "Location": {
                        "X": 0.0,
                        "Y": 0.0,
                        "Z": 0.0
                      },
                      "Rotation": {
                        "Pitch": 0.0,
                        "Yaw": 0.0,
                        "Roll": 0.0
                      }
                    },
                    "AdjustRootMotionInfoArray": [],
                    "FaceTargetInfoArray": [
                      {
                        "AnimSequenceName": "AS_E024_FFF_ACT_Charge",
                        "NotifyName": "NST_FaceTarget_C_0",
                        "BeginNotifyTime": 0.6166419,
                        "EndNotifyTime": 0.0,
                        "YawOffset": 0.0
                      }
                    ],
                    "ProjectileRange": 3000.0
                  }
                }
              ]
            }
          },
          {
            "CoopActionStart": {
              "ActionDerivationArray": [
                {
                  "Key": {
                    "Type": "ESBCharacterAnimationSamplingResultActionDerivedType::Default",
                    "ThresholdVelocity": 0.0,
                    "CommandArray": []
                  },
                  "ActionData": {
                    "AttackInfos": [],
                    "UseAnimationAssetPath": [],
                    "AnimTime": 1.4166111,
                    "LocationAndRotation": {
                      "Location": {
                        "X": 0.0,
                        "Y": 0.0,
                        "Z": 0.0
                      },
                      "Rotation": {
                        "Pitch": 0.0,
                        "Yaw": 0.0,
                        "Roll": 0.0
                      }
                    },
                    "AdjustRootMotionInfoArray": [],
                    "FaceTargetInfoArray": [],
                    "ProjectileRange": 3000.0
                  }
                }
              ]
            }
          },
          {
            "CoopActionSpell": {
              "ActionDerivationArray": [
                {
                  "Key": {
                    "Type": "ESBCharacterAnimationSamplingResultActionDerivedType::Default",
                    "ThresholdVelocity": 0.0,
                    "CommandArray": []
                  },
                  "ActionData": {
                    "AttackInfos": [],
                    "UseAnimationAssetPath": [],
                    "AnimTime": 10.966281,
                    "LocationAndRotation": {
                      "Location": {
                        "X": 0.0,
                        "Y": 0.0,
                        "Z": 0.0
                      },
                      "Rotation": {
                        "Pitch": 0.0,
                        "Yaw": 0.0,
                        "Roll": 0.0
                      }
                    },
                    "AdjustRootMotionInfoArray": [],
                    "FaceTargetInfoArray": [],
                    "ProjectileRange": 3000.0
                  }
                }
              ]
            }
          }
        ],
        "AnimationSequenceGroupMap": [
          {
            "/Game/Animations/Enemy/E024/AS_E024_FFF_ACT_BlowDw": {
              "NotifyStateGroupMap": [
                {
                  "NST_FaceTarget_C_0": {
                    "BeginNotifyTime": 0.016666,
                    "EndNotifyTime": 0.9499618
                  }
                },
                {
                  "SBAnimNotifyState_SuperArmor_0": {
                    "BeginNotifyTime": 0.016666,
                    "EndNotifyTime": 1.1666203
                  }
                },
                {
                  "SBAnimNotifyState_AdjustEnemyRootMotion_0": {
                    "BeginNotifyTime": 0.99995977,
                    "EndNotifyTime": 1.1666203
                  }
                }
              ]
            }
          },
          {
            "/Game/Animations/Enemy/E024/AS_E024_FFF_ACT_Charge_Start": {
              "NotifyStateGroupMap": [
                {
                  "SBAnimNotifyState_SuperArmor_0": {
                    "BeginNotifyTime": 0.016666,
                    "EndNotifyTime": 0.6166419
                  }
                }
              ]
            }
          },
          {
            "/Game/Animations/Enemy/E024/AS_E024_FFF_ACT_Charge": {
              "NotifyStateGroupMap": [
                {
                  "NST_FaceTarget_C_0": {
                    "BeginNotifyTime": 0.6166419,
                    "EndNotifyTime": 5.649763
                  }
                },
                {
                  "SBAnimNotifyState_SuperArmor_0": {
                    "BeginNotifyTime": 0.6166419,
                    "EndNotifyTime": 5.649763
                  }
                }
              ]
            }
          },
          {
            "/Game/Animations/Enemy/E024/AS_E024_FFF_ACT_LightLaserbeam": {
              "NotifyStateGroupMap": [
                {
                  "SBAnimNotifyState_SuperArmor_0": {
                    "BeginNotifyTime": 2.6832263,
                    "EndNotifyTime": 2.74989
                  }
                }
              ]
            }
          },
          {
            "/Game/Animations/Enemy/E024/AS_E024_FFF_LOC_DodgeB": {
              "NotifyStateGroupMap": [
                {
                  "NST_FaceTarget_C_2": {
                    "BeginNotifyTime": 0.083330005,
                    "EndNotifyTime": 0.4999799
                  }
                }
              ]
            }
          },
          {
            "/Game/Animations/Enemy/E024/AS_E024_FFF_LOC_DodgeL": {
              "NotifyStateGroupMap": [
                {
                  "SBAnimNotifyState_EnemyLookAt_0": {
                    "BeginNotifyTime": 0.0,
                    "EndNotifyTime": 0.64997387
                  }
                },
                {
                  "NST_FaceTarget_C_2": {
                    "BeginNotifyTime": 0.09999601,
                    "EndNotifyTime": 0.4999799
                  }
                }
              ]
            }
          },
          {
            "/Game/Animations/Enemy/E024/AS_E024_FFF_LOC_DodgeR": {
              "NotifyStateGroupMap": [
                {
                  "SBAnimNotifyState_EnemyLookAt_0": {
                    "BeginNotifyTime": 0.0,
                    "EndNotifyTime": 0.64997387
                  }
                },
                {
                  "NST_FaceTarget_C_2": {
                    "BeginNotifyTime": 0.083330005,
                    "EndNotifyTime": 0.4999799
                  }
                }
              ]
            }
          },
          {
            "/Game/Animations/Enemy/E024/AS_E024_FFF_ACT_Jump": {
              "NotifyStateGroupMap": [
                {
                  "SBAnimNotifyState_AdjustEnemyRootMotion_0": {
                    "BeginNotifyTime": 0.0,
                    "EndNotifyTime": 0.43331593
                  }
                },
                {
                  "SBAnimNotifyState_AdjustEnemyRootMotion_1": {
                    "BeginNotifyTime": 0.39998394,
                    "EndNotifyTime": 0.69997185
                  }
                }
              ]
            }
          },
          {
            "/Game/Animations/Enemy/E024/AS_E024_PDH_ACT_ChantStartCoopAction": {
              "NotifyStateGroupMap": [
                {
                  "SBAnimNotifyState_SuperArmor_0": {
                    "BeginNotifyTime": 0.0,
                    "EndNotifyTime": 0.6166419
                  }
                },
                {
                  "SBAnimNotifyState_CoopActionPowerSupply_0": {
                    "BeginNotifyTime": 0.29998797,
                    "EndNotifyTime": 0.5999759
                  }
                }
              ]
            }
          },
          {
            "/Game/Animations/Enemy/E024/AS_E024_PDH_ACT_ChantCoopAction": {
              "NotifyStateGroupMap": [
                {
                  "SBAnimNotifyState_SuperArmor_0": {
                    "BeginNotifyTime": 0.6166419,
                    "EndNotifyTime": 9.216308
                  }
                },
                {
                  "SBAnimNotifyState_CoopActionPowerSupply_0": {
                    "BeginNotifyTime": 0.6166419,
                    "EndNotifyTime": 9.216308
                  }
                }
              ]
            }
          },
          {
            "/Game/Animations/Enemy/E024/AS_E024_PDH_ACT_CastCoopAction": {
              "NotifyStateGroupMap": [
                {
                  "SBAnimNotifyState_SuperArmor_0": {
                    "BeginNotifyTime": 9.216308,
                    "EndNotifyTime": 9.416305
                  }
                }
              ]
            }
          }
        ]
      }
    }
  }
]